setup.py
prob_dist_simplified/Binomialdistribution.py
prob_dist_simplified/Gaussiandistribution.py
prob_dist_simplified/Generaldistribution.py
prob_dist_simplified/__init__.py
prob_dist_simplified.egg-info/PKG-INFO
prob_dist_simplified.egg-info/SOURCES.txt
prob_dist_simplified.egg-info/dependency_links.txt
prob_dist_simplified.egg-info/not-zip-safe
prob_dist_simplified.egg-info/top_level.txt