Metadata-Version: 1.0
Name: prob-dist-simplified
Version: 1.0
Summary: Probability Distributions
Home-page: UNKNOWN
Author: Sakzsee
Author-email: UNKNOWN
License: UNKNOWN
Platform: UNKNOWN
